counter.sv
module counter #(
  parameter WIDTH = 8
)(
  // interface signals
  input  logic             clk,      // clock
  input  logic             rst,      // reset
  input  logic             ld,       // load counter from data
  input  logic [WIDTH-1:0] v,        // value to preload
  output logic [WIDTH-1:0] count     // count output
);

always_ff @ (posedge clk)
  if (rst) count <= {v};
  else     count <= ld ? v : count + {{WIDTH-1{1'b0}},1'b1};
endmodule

counter.vcd
$version Generated by VerilatedVcd $end
$date Wed Oct 23 17:59:35 2024 $end
$timescale 1ps $end

 $scope module TOP $end
  $var wire  1 # clk $end
  $var wire  8 ' count [7:0] $end
  $var wire  1 % ld $end
  $var wire  1 $ rst $end
  $var wire  8 & v [7:0] $end
  $scope module counter $end
   $var wire 32 ( WIDTH [31:0] $end
   $var wire  1 # clk $end
   $var wire  8 ' count [7:0] $end
   $var wire  1 % ld $end
   $var wire  1 $ rst $end
   $var wire  8 & v [7:0] $end
  $upscope $end
 $upscope $end
$enddefinitions $end


#0
1#
1$
0%
b00110011 &
b00000000 '
b00000000000000000000000000001000 (
#1
0#
#2
1#
1%
b00110011 '
#3
0#
#4
1#
#5
0#
#6
1#
0$
#7
0#
#8
1#
#9
0#
#10
1#
#11
0#
#12
1#
#13
0#
#14
1#
#15
0#
#16
1#
#17
0#
#18
1#
#19
0#
#20
1#
#21
0#
#22
1#
#23
0#
#24
1#
#25
0#
#26
1#
#27
0#
#28
1#
#29
0#
#30
1#
#31
0#
#32
1#
1$
#33
0#
#34
1#
0$
#35
0#
#36
1#
#37
0#
#38
1#
0%
#39
0#
#40
1#
b00110100 '
#41
0#
#42
1#
b00110101 '
#43
0#
#44
1#
b00110110 '
#45
0#
#46
1#
b00110111 '
#47
0#
#48
1#
b00111000 '
#49
0#
#50
1#
b00111001 '
#51
0#
#52
1#
1%
b00111010 '
#53
0#
#54
1#
b00110011 '
